{
    "journalName": " asdf",
    "logs": [
        {
            "logTitle": "asdf",
            "logDate": "sadf",
            "logEntry": "asdf"
        },
        {
            "logTitle": " adsf",
            "logDate": " sdaf",
            "logEntry": " asdf"
        },
        {
            "logTitle": " asdf",
            "logDate": " asdf",
            "logEntry": " adsf"
        },
        {
            "logTitle": " asdf",
            "logDate": " sdaf",
            "logEntry": " asdf"
        },
        {
            "logTitle": " asdf",
            "logDate": " asdf",
            "logEntry": " asdf"
        },
        {
            "logTitle": " asdf",
            "logDate": " asdf",
            "logEntry": " asdf"
        }
    ]
}